Metadata-Version: 2.1
Name: Tergame
Version: 0.0.2
Summary: Make text-based command line games using this module.
Home-page: https://bruhdev.com
Author: BruhDev
Author-email: mr.bruh.dev@gmail.com
License: UNKNOWN
Platform: UNKNOWN
Requires-Python: >=3.7
